README.md
compiler-submit
compiler-test
compiler-test-setup
setup.py
ShanghaiTech_compiler_judger.egg-info/PKG-INFO
ShanghaiTech_compiler_judger.egg-info/SOURCES.txt
ShanghaiTech_compiler_judger.egg-info/dependency_links.txt
ShanghaiTech_compiler_judger.egg-info/not-zip-safe
ShanghaiTech_compiler_judger.egg-info/requires.txt
ShanghaiTech_compiler_judger.egg-info/top_level.txt
compiler_client/__init__.py