Metadata-Version: 2.1
Name: ShanghaiTech-compiler-judger
Version: 0.0.3
Summary: Tools for ShanghaiTech Compiler course. 
Home-page: UNKNOWN
Author: Q7
Author-email: q71998@gmail.com
License: MIT
Platform: UNKNOWN
Classifier: Development Status :: 3 - Alpha
Classifier: Intended Audience :: Developers
Classifier: Intended Audience :: Science/Research
Classifier: License :: OSI Approved :: MIT License
Classifier: Programming Language :: Python :: 3
Classifier: Programming Language :: Python :: 3.5
Classifier: Programming Language :: Python :: 3.6
Provides-Extra: testing
